http_requests_viewer/__init__.py
http_requests_viewer/admin.py
http_requests_viewer/apps.py
http_requests_viewer/extractor.py
http_requests_viewer/forms.py
http_requests_viewer/models.py
http_requests_viewer/tests.py
http_requests_viewer/urls.py
http_requests_viewer/views.py
http_requests_viewer/migrations/0001_initial.py
http_requests_viewer/migrations/__init__.py
http_requests_viewer/templates/http_requests_viewer/agent_list_n_create.html
http_requests_viewer/templates/http_requests_viewer/base.html
http_requests_viewer/templates/http_requests_viewer/delete_form.html
http_requests_viewer/templates/http_requests_viewer/nav.html
http_requests_viewer/templates/http_requests_viewer/request_detail.html
http_requests_viewer/templates/http_requests_viewer/target_create.html
http_requests_viewer/templates/http_requests_viewer/target_detail.html
http_requests_viewer/templates/http_requests_viewer/target_list.html
http_requests_viewer/templatetags/__init__.py
http_requests_viewer/templatetags/http_requests_viewer.py
http_requests_viewer-0.1.dist-info/LICENSE
http_requests_viewer-0.1.dist-info/METADATA
http_requests_viewer-0.1.dist-info/WHEEL
http_requests_viewer-0.1.dist-info/top_level.txt
http_requests_viewer-0.1.dist-info/RECORD
