Metadata-Version: 2.1
Name: http-requests-viewer
Version: 0.1
Summary: A Django app to view http(s) from a driver session.
Home-page: https://github.com/tinnguyen18920/http-requests-viewer
Author: tinnguyen18920
Author-email: tinnguyen18920@gmail.com
License: BSD-3-Clause
Platform: UNKNOWN
Classifier: Programming Language :: Python :: 3
Classifier: License :: OSI Approved :: BSD License
Classifier: Operating System :: OS Independent
Requires-Python: >=3.9
Requires-Dist: user-agents (>=2.2.0)
Requires-Dist: selenium (>=3.141.0)
Requires-Dist: selenium-wire (>=4.2.4)
Requires-Dist: django-bootstrap4 (>=3.0.1)
